apriltags_eth.cpython-311-x86_64-linux-gnu.so
apriltags2_ethz-0.9.5.dist-info/METADATA
apriltags2_ethz-0.9.5.dist-info/LICENSE
apriltags2_ethz-0.9.5.dist-info/top_level.txt
apriltags2_ethz-0.9.5.dist-info/WHEEL
apriltags2_ethz-0.9.5.dist-info/RECORD
apriltags2_ethz.libs/libv4l2-73b3e8ef.so.0.0.0
apriltags2_ethz.libs/libopencv_core-e07fff4f.so.3.4.6
apriltags2_ethz.libs/libopencv_stitching-5bb22b42.so.3.4.6
apriltags2_ethz.libs/libopencv_saliency-9c084d3e.so.3.4.6
apriltags2_ethz.libs/libpng16-748299c7.so.16.34.0
apriltags2_ethz.libs/libopencv_highgui-50d13364.so.3.4.6
apriltags2_ethz.libs/libicudata-05640f77.so.60.3
apriltags2_ethz.libs/libopencv_calib3d-a5df74ce.so.3.4.6
apriltags2_ethz.libs/libsystemd-cbb43bdb.so.0.23.0
apriltags2_ethz.libs/libjasper-2f9728df.so.4.0.0
apriltags2_ethz.libs/libopencv_bgsegm-cd62a0eb.so.3.4.6
apriltags2_ethz.libs/libdc1394-68c67e1a.so.22.1.9
apriltags2_ethz.libs/libbz2-e34b29ae.so.1.0.6
apriltags2_ethz.libs/libopencv_reg-c7d210fb.so.3.4.6
apriltags2_ethz.libs/libQt5Core-5071b297.so.5.15.3
apriltags2_ethz.libs/libpcre2-16-bca4e6b3.so.0.7.1
apriltags2_ethz.libs/libva-ed3913e3.so.2.1300.0
apriltags2_ethz.libs/libopencv_structured_light-834603ec.so.3.4.6
apriltags2_ethz.libs/libopencv_hfs-c4872bf0.so.3.4.6
apriltags2_ethz.libs/libtesseract-36bdf404.so.4.0.1
apriltags2_ethz.libs/libquadmath-895c7c83.so.0.0.0
apriltags2_ethz.libs/libv4lconvert-f41b53fd.so.0.0.0
apriltags2_ethz.libs/libopencv_dnn-c9b5bb21.so.3.4.6
apriltags2_ethz.libs/libgmp-452f15e0.so.10.3.2
apriltags2_ethz.libs/libopencv_videoio-1144a636.so.3.4.6
apriltags2_ethz.libs/libgstapp-1-4367e2ba.0.so.0.1601.0
apriltags2_ethz.libs/libgif-5ed6ffef.so.7.0.0
apriltags2_ethz.libs/libfribidi-a2ddad26.so.0.4.0
apriltags2_ethz.libs/libopencv_videostab-9b557600.so.3.4.6
apriltags2_ethz.libs/libtiff-c437d1e6.so.5.3.0
apriltags2_ethz.libs/libopencv_xphoto-279770f2.so.3.4.6
apriltags2_ethz.libs/libopencv_rgbd-c583c7f8.so.3.4.6
apriltags2_ethz.libs/libopencv_aruco-a35b44a0.so.3.4.6
apriltags2_ethz.libs/libucil-4912afad.so.2.4.0
apriltags2_ethz.libs/libjpeg-da649728.so.62.2.0
apriltags2_ethz.libs/libblkid-c8769086.so.1.1.0
