Metadata-Version: 2.1
Name: apriltags2-ethz
Version: 0.9.5
Author: Jariullah Safi
Author-email: safijari@isu.edu
License-File: LICENSE
Requires-Dist: pybind11 >=2.2
Requires-Dist: numpy
Requires-Dist: opencv-python
Requires-Dist: argh
